odoo/addons/stock_picking_grn_mandatory/README.rst
odoo/addons/stock_picking_grn_mandatory/__init__.py
odoo/addons/stock_picking_grn_mandatory/__manifest__.py
odoo/addons/stock_picking_grn_mandatory/i18n/es.po
odoo/addons/stock_picking_grn_mandatory/i18n/it.po
odoo/addons/stock_picking_grn_mandatory/i18n/stock_picking_grn_mandatory.pot
odoo/addons/stock_picking_grn_mandatory/models/__init__.py
odoo/addons/stock_picking_grn_mandatory/models/stock_picking.py
odoo/addons/stock_picking_grn_mandatory/models/stock_picking_type.py
odoo/addons/stock_picking_grn_mandatory/readme/CONFIGURE.rst
odoo/addons/stock_picking_grn_mandatory/readme/CONTRIBUTORS.rst
odoo/addons/stock_picking_grn_mandatory/readme/DESCRIPTION.rst
odoo/addons/stock_picking_grn_mandatory/readme/USAGE.rst
odoo/addons/stock_picking_grn_mandatory/static/description/icon.png
odoo/addons/stock_picking_grn_mandatory/static/description/index.html
odoo/addons/stock_picking_grn_mandatory/tests/__init__.py
odoo/addons/stock_picking_grn_mandatory/tests/test_grn_mandatory.py
odoo/addons/stock_picking_grn_mandatory/views/stock_picking_type.xml
odoo_addon_stock_picking_grn_mandatory-16.0.1.1.0.dist-info/METADATA
odoo_addon_stock_picking_grn_mandatory-16.0.1.1.0.dist-info/WHEEL
odoo_addon_stock_picking_grn_mandatory-16.0.1.1.0.dist-info/top_level.txt
odoo_addon_stock_picking_grn_mandatory-16.0.1.1.0.dist-info/RECORD
