Metadata-Version: 2.1
Name: odoo-addon-stock_picking_grn_mandatory
Version: 16.0.1.1.0
Summary: This module allows to require a GRN (Goods Receive Note) when doing a Stock Picking
Home-page: https://github.com/OCA/stock-logistics-workflow
Author: ACSONE SA/NV,Odoo Community Association (OCA)
Author-email: support@odoo-community.org
License: AGPL-3
Classifier: Programming Language :: Python
Classifier: Framework :: Odoo
Classifier: Framework :: Odoo :: 16.0
Classifier: License :: OSI Approved :: GNU Affero General Public License v3
Requires-Python: >=3.10
Requires-Dist: odoo-addon-stock-grn<16.1dev,>=16.0dev
Requires-Dist: odoo<16.1dev,>=16.0a
